PlusAPI/PlusAPI.py
PlusAPI/__init__.py
PlusAPI-0.0.2.dist-info/LICENSE
PlusAPI-0.0.2.dist-info/METADATA
PlusAPI-0.0.2.dist-info/WHEEL
PlusAPI-0.0.2.dist-info/top_level.txt
PlusAPI-0.0.2.dist-info/RECORD
