Metadata-Version: 2.1
Name: PlusAPI
Version: 0.0.2
Summary: PlusAPI | Piyasa Verileri | Python
Home-page: https://github.com/keyiflerolsun/PlusAPI
Author: keyiflerolsun
Author-email: keyiflerolsun@gmail.com
License: GPLv3+
Keywords: PlusAPI,HisseVeri,KriptoVeri
Platform: UNKNOWN
Classifier: Development Status :: 5 - Production/Stable
Classifier: License :: OSI Approved :: GNU General Public License v3 or later (GPLv3+)
Classifier: Programming Language :: Python :: 3
Requires-Python: >=3.6
License-File: LICENSE
Requires-Dist: requests-html
Requires-Dist: simplejson
